BF2PALM/OSM2PALM.py
BF2PALM/__init__.py
BF2PALM/__main__.py
BF2PALM/allall.py
BF2PALM/cal_WGSdist.py
BF2PALM/cal_alignness.py
BF2PALM/cal_lf.py
BF2PALM/cal_variance.py
BF2PALM/centroid.py
BF2PALM/convert.py
BF2PALM/edgeDetection.py
BF2PALM/entropy.py
BF2PALM/evalgeo.py
BF2PALM/extractDomainOSM.py
BF2PALM/geo.py
BF2PALM/noHoles.py
BF2PALM/rasterization.py
BF2PALM/results.py
BF2PALM/rotate.py
BF2PALM/selectRegion.py
BF2PALM/settings.py
BF2PALM/shear.py
BF2PALM/showDiagram.py
BF2PALM-0.0.37.dist-info/LICENSE.txt
BF2PALM-0.0.37.dist-info/METADATA
BF2PALM-0.0.37.dist-info/WHEEL
BF2PALM-0.0.37.dist-info/top_level.txt
BF2PALM-0.0.37.dist-info/RECORD
